{"namespaces":{
  "corebit":{
    "modules":{
      "const":{
        "type":["Record",[
          ["out","Bit"]
        ]],
        "modparams":{"value":"Bool"}
      }
    }
  },
  "coreir":{
    "generators":{
      "const":{
        "typegen":"coreir.singleOutType",
        "genparams":{"width":"Int"},
        "modules":[
          [
            {"width":["Int",55]},
            {
              "type":["Record",[
                ["out",["Array",55,"Bit"]]
              ]],
              "modparams":{"value":["BitVector",55]}
            }
          ]
        ]
      }
    },
    "typegens":{
      "singleOutType":[
        {"width":"Int"},
        "sparse",
        [
          [{"width":["Int",55]},["Record",[["out",["Array",55,"Bit"]]]]]
        ]
      ]
    }
  },
  "global":{
    "modules":{
      "PE":{
        "type":["Record",[
          ["inst",["Array",55,"BitIn"]],
          ["inputs0",["Array",16,"BitIn"]],
          ["inputs1",["Array",16,"BitIn"]],
          ["inputs2","BitIn"],
          ["inputs3","BitIn"],
          ["inputs4","BitIn"],
          ["clk_en","BitIn"],
          ["O0",["Array",16,"Bit"]],
          ["O1","Bit"],
          ["CLK",["Named","coreir.clkIn"]],
          ["ASYNCRESET",["Named","coreir.arstIn"]]
        ]]
      },
      "hcompute_cim_output_stencil":{
        "type":["Record",[
          ["in0_cim_stencil",["Array",9,["Array",16,"BitIn"]]],
          ["out_cim_output_stencil",["Array",16,"Bit"]]
        ]],
        "instances":{
          "c140147517936400":{
            "modref":"corebit.const",
            "modargs":{"value":["Bool",true]}
          },
          "c140147517938768":{
            "genref":"coreir.const",
            "genargs":{"width":["Int",55]},
            "modargs":{"value":[["BitVector",55],"55'h600000000c1085"]}
          },
          "c140147517993360":{
            "modref":"corebit.const",
            "modargs":{"value":["Bool",true]}
          },
          "c140147517994256":{
            "modref":"corebit.const",
            "modargs":{"value":["Bool",true]}
          },
          "c140147517995408":{
            "modref":"corebit.const",
            "modargs":{"value":["Bool",true]}
          },
          "c140147517996368":{
            "genref":"coreir.const",
            "genargs":{"width":["Int",55]},
            "modargs":{"value":[["BitVector",55],"55'h000c000004b000"]}
          },
          "c140147517996880":{
            "genref":"coreir.const",
            "genargs":{"width":["Int",55]},
            "modargs":{"value":[["BitVector",55],"55'h000c000004b000"]}
          },
          "c140147518415632":{
            "genref":"coreir.const",
            "genargs":{"width":["Int",55]},
            "modargs":{"value":[["BitVector",55],"55'h600000000c1085"]}
          },
          "c140147518417680":{
            "modref":"corebit.const",
            "modargs":{"value":["Bool",true]}
          },
          "c140147518418256":{
            "modref":"corebit.const",
            "modargs":{"value":["Bool",true]}
          },
          "c140147527304272":{
            "modref":"corebit.const",
            "modargs":{"value":["Bool",true]}
          },
          "c140147527306448":{
            "genref":"coreir.const",
            "genargs":{"width":["Int",55]},
            "modargs":{"value":[["BitVector",55],"55'h600000000c1085"]}
          },
          "c140147530402960":{
            "genref":"coreir.const",
            "genargs":{"width":["Int",55]},
            "modargs":{"value":[["BitVector",55],"55'h0000200ff5294a"]}
          },
          "c140147534225808":{
            "genref":"coreir.const",
            "genargs":{"width":["Int",55]},
            "modargs":{"value":[["BitVector",55],"55'h000c000004b000"]}
          },
          "c140147534226192":{
            "modref":"corebit.const",
            "modargs":{"value":["Bool",true]}
          },
          "c140147534226704":{
            "genref":"coreir.const",
            "genargs":{"width":["Int",55]},
            "modargs":{"value":[["BitVector",55],"55'h000c000004b000"]}
          },
          "c140147534227344":{
            "modref":"corebit.const",
            "modargs":{"value":["Bool",true]}
          },
          "c140147534228176":{
            "genref":"coreir.const",
            "genargs":{"width":["Int",55]},
            "modargs":{"value":[["BitVector",55],"55'h000c000004b000"]}
          },
          "c140147534228432":{
            "modref":"corebit.const",
            "modargs":{"value":["Bool",true]}
          },
          "c140147534229072":{
            "modref":"corebit.const",
            "modargs":{"value":["Bool",true]}
          },
          "c140147534229264":{
            "genref":"coreir.const",
            "genargs":{"width":["Int",55]},
            "modargs":{"value":[["BitVector",55],"55'h000c000004b000"]}
          },
          "c140147534260752":{
            "genref":"coreir.const",
            "genargs":{"width":["Int",55]},
            "modargs":{"value":[["BitVector",55],"55'h600000000c1085"]}
          },
          "c140147537191568":{
            "modref":"corebit.const",
            "modargs":{"value":["Bool",true]}
          },
          "c140147537191632":{
            "genref":"coreir.const",
            "genargs":{"width":["Int",55]},
            "modargs":{"value":[["BitVector",55],"55'h7f8400000cd739"]}
          },
          "c140147537191760":{
            "modref":"corebit.const",
            "modargs":{"value":["Bool",true]}
          },
          "c140147537192336":{
            "genref":"coreir.const",
            "genargs":{"width":["Int",55]},
            "modargs":{"value":[["BitVector",55],"55'h000c000004b000"]}
          },
          "c140147537192464":{
            "genref":"coreir.const",
            "genargs":{"width":["Int",55]},
            "modargs":{"value":[["BitVector",55],"55'h000c000004b000"]}
          },
          "c140147537194064":{
            "genref":"coreir.const",
            "genargs":{"width":["Int",55]},
            "modargs":{"value":[["BitVector",55],"55'h0000200015294a"]}
          },
          "c140147537194128":{
            "modref":"corebit.const",
            "modargs":{"value":["Bool",true]}
          },
          "c140147537194320":{
            "modref":"corebit.const",
            "modargs":{"value":["Bool",true]}
          },
          "c140147537194832":{
            "modref":"corebit.const",
            "modargs":{"value":["Bool",true]}
          },
          "c140147539051280":{
            "modref":"corebit.const",
            "modargs":{"value":["Bool",true]}
          },
          "c140147539051472":{
            "genref":"coreir.const",
            "genargs":{"width":["Int",55]},
            "modargs":{"value":[["BitVector",55],"55'h600000000c1085"]}
          },
          "c140147539051792":{
            "modref":"corebit.const",
            "modargs":{"value":["Bool",true]}
          },
          "c140147539052112":{
            "genref":"coreir.const",
            "genargs":{"width":["Int",55]},
            "modargs":{"value":[["BitVector",55],"55'h600000000c1085"]}
          },
          "c140147539052432":{
            "genref":"coreir.const",
            "genargs":{"width":["Int",55]},
            "modargs":{"value":[["BitVector",55],"55'h600000000c1085"]}
          },
          "c140147539053776":{
            "genref":"coreir.const",
            "genargs":{"width":["Int",55]},
            "modargs":{"value":[["BitVector",55],"55'h600000000c1085"]}
          },
          "c140147544467344":{
            "genref":"coreir.const",
            "genargs":{"width":["Int",55]},
            "modargs":{"value":[["BitVector",55],"55'h003830000518c5"]}
          },
          "c140147548999760":{
            "modref":"corebit.const",
            "modargs":{"value":["Bool",true]}
          },
          "c140147549000208":{
            "modref":"corebit.const",
            "modargs":{"value":["Bool",true]}
          },
          "c140147549002512":{
            "modref":"corebit.const",
            "modargs":{"value":["Bool",true]}
          },
          "c140147549002768":{
            "genref":"coreir.const",
            "genargs":{"width":["Int",55]},
            "modargs":{"value":[["BitVector",55],"55'h0000200005294a"]}
          },
          "i140147527092368_i140147520751376":{
            "modref":"global.PE"
          },
          "i140147531441616_i140147520054672":{
            "modref":"global.PE"
          },
          "i140147531441744_i140147520992400":{
            "modref":"global.PE"
          },
          "i140147531442896_i140147520992400":{
            "modref":"global.PE"
          },
          "i140147531443600_i140147543025168":{
            "modref":"global.PE"
          },
          "i140147531448976_i140147520054672":{
            "modref":"global.PE"
          },
          "i140147531449872_i140147520992400":{
            "modref":"global.PE"
          },
          "i140147531449936_i140147520054672":{
            "modref":"global.PE"
          },
          "i140147531451024_i140147520992400":{
            "modref":"global.PE"
          },
          "i140147531451984_i140147520054672":{
            "modref":"global.PE"
          },
          "i140147531493584_i140147520043280":{
            "modref":"global.PE"
          },
          "i140147531494416_i140147520043280":{
            "modref":"global.PE"
          },
          "i140147531496784_i140147520043280":{
            "modref":"global.PE"
          },
          "i140147531515472_i140147520992400":{
            "modref":"global.PE"
          },
          "i140147531515664_i140147520054672":{
            "modref":"global.PE"
          },
          "i140147531535632_i140147520992400":{
            "modref":"global.PE"
          },
          "i140147531535696_i140147520054672":{
            "modref":"global.PE"
          },
          "i140147531535760_i140147520992400":{
            "modref":"global.PE"
          },
          "i140147531535824_i140147520992400":{
            "modref":"global.PE"
          },
          "i140147531536336_i140147520054672":{
            "modref":"global.PE"
          },
          "i140147531536464_i140147520054672":{
            "modref":"global.PE"
          }
        },
        "connections":[
          ["i140147531451024_i140147520992400.clk_en","c140147517936400.out"],
          ["i140147531535824_i140147520992400.inst","c140147517938768.out"],
          ["i140147531449872_i140147520992400.clk_en","c140147517993360.out"],
          ["i140147531449936_i140147520054672.clk_en","c140147517994256.out"],
          ["i140147531442896_i140147520992400.clk_en","c140147517995408.out"],
          ["i140147531449936_i140147520054672.inst","c140147517996368.out"],
          ["i140147531451984_i140147520054672.inst","c140147517996880.out"],
          ["i140147531535632_i140147520992400.inst","c140147518415632.out"],
          ["i140147531535824_i140147520992400.clk_en","c140147518417680.out"],
          ["i140147531535632_i140147520992400.clk_en","c140147518418256.out"],
          ["i140147531441744_i140147520992400.clk_en","c140147527304272.out"],
          ["i140147531441744_i140147520992400.inst","c140147527306448.out"],
          ["i140147531496784_i140147520043280.inst","c140147530402960.out"],
          ["i140147531515664_i140147520054672.inst","c140147534225808.out"],
          ["i140147531451984_i140147520054672.clk_en","c140147534226192.out"],
          ["i140147531441616_i140147520054672.inst","c140147534226704.out"],
          ["i140147531441616_i140147520054672.clk_en","c140147534227344.out"],
          ["i140147531535696_i140147520054672.inst","c140147534228176.out"],
          ["i140147531515664_i140147520054672.clk_en","c140147534228432.out"],
          ["i140147531535696_i140147520054672.clk_en","c140147534229072.out"],
          ["i140147531536464_i140147520054672.inst","c140147534229264.out"],
          ["i140147531451024_i140147520992400.inst","c140147534260752.out"],
          ["i140147531448976_i140147520054672.clk_en","c140147537191568.out"],
          ["i140147531443600_i140147543025168.inst","c140147537191632.out"],
          ["i140147531494416_i140147520043280.clk_en","c140147537191760.out"],
          ["i140147531448976_i140147520054672.inst","c140147537192336.out"],
          ["i140147531536336_i140147520054672.inst","c140147537192464.out"],
          ["i140147531494416_i140147520043280.inst","c140147537194064.out"],
          ["i140147531536336_i140147520054672.clk_en","c140147537194128.out"],
          ["i140147531443600_i140147543025168.clk_en","c140147537194320.out"],
          ["i140147531536464_i140147520054672.clk_en","c140147537194832.out"],
          ["i140147531535760_i140147520992400.clk_en","c140147539051280.out"],
          ["i140147531515472_i140147520992400.inst","c140147539051472.out"],
          ["i140147531515472_i140147520992400.clk_en","c140147539051792.out"],
          ["i140147531442896_i140147520992400.inst","c140147539052112.out"],
          ["i140147531449872_i140147520992400.inst","c140147539052432.out"],
          ["i140147531535760_i140147520992400.inst","c140147539053776.out"],
          ["i140147527092368_i140147520751376.inst","c140147544467344.out"],
          ["i140147527092368_i140147520751376.clk_en","c140147548999760.out"],
          ["i140147531493584_i140147520043280.clk_en","c140147549000208.out"],
          ["i140147531496784_i140147520043280.clk_en","c140147549002512.out"],
          ["i140147531493584_i140147520043280.inst","c140147549002768.out"],
          ["self.out_cim_output_stencil","i140147527092368_i140147520751376.O0"],
          ["i140147531496784_i140147520043280.O0","i140147527092368_i140147520751376.inputs0"],
          ["i140147531493584_i140147520043280.O0","i140147527092368_i140147520751376.inputs1"],
          ["i140147531441744_i140147520992400.O1","i140147527092368_i140147520751376.inputs2"],
          ["i140147531442896_i140147520992400.inputs4","i140147531441616_i140147520054672.O1"],
          ["self.in0_cim_stencil.1","i140147531441616_i140147520054672.inputs0"],
          ["self.in0_cim_stencil.3","i140147531441616_i140147520054672.inputs1"],
          ["i140147531451024_i140147520992400.O1","i140147531441744_i140147520992400.inputs3"],
          ["i140147531443600_i140147543025168.O1","i140147531441744_i140147520992400.inputs4"],
          ["i140147531515472_i140147520992400.inputs3","i140147531442896_i140147520992400.O1"],
          ["i140147531449872_i140147520992400.O1","i140147531442896_i140147520992400.inputs3"],
          ["self.in0_cim_stencil.1","i140147531443600_i140147543025168.inputs0"],
          ["i140147531494416_i140147520043280.O0","i140147531443600_i140147543025168.inputs1"],
          ["i140147531451024_i140147520992400.inputs4","i140147531448976_i140147520054672.O1"],
          ["self.in0_cim_stencil.1","i140147531448976_i140147520054672.inputs0"],
          ["self.in0_cim_stencil.8","i140147531448976_i140147520054672.inputs1"],
          ["i140147531449936_i140147520054672.O1","i140147531449872_i140147520992400.inputs3"],
          ["i140147531451984_i140147520054672.O1","i140147531449872_i140147520992400.inputs4"],
          ["self.in0_cim_stencil.1","i140147531449936_i140147520054672.inputs0"],
          ["self.in0_cim_stencil.0","i140147531449936_i140147520054672.inputs1"],
          ["i140147531535824_i140147520992400.O1","i140147531451024_i140147520992400.inputs3"],
          ["self.in0_cim_stencil.1","i140147531451984_i140147520054672.inputs0"],
          ["self.in0_cim_stencil.2","i140147531451984_i140147520054672.inputs1"],
          ["i140147531535760_i140147520992400.inputs3","i140147531515472_i140147520992400.O1"],
          ["i140147531515664_i140147520054672.O1","i140147531515472_i140147520992400.inputs4"],
          ["self.in0_cim_stencil.1","i140147531515664_i140147520054672.inputs0"],
          ["self.in0_cim_stencil.4","i140147531515664_i140147520054672.inputs1"],
          ["i140147531535824_i140147520992400.inputs3","i140147531535632_i140147520992400.O1"],
          ["i140147531535760_i140147520992400.O1","i140147531535632_i140147520992400.inputs3"],
          ["i140147531536464_i140147520054672.O1","i140147531535632_i140147520992400.inputs4"],
          ["i140147531535760_i140147520992400.inputs4","i140147531535696_i140147520054672.O1"],
          ["self.in0_cim_stencil.1","i140147531535696_i140147520054672.inputs0"],
          ["self.in0_cim_stencil.5","i140147531535696_i140147520054672.inputs1"],
          ["i140147531536336_i140147520054672.O1","i140147531535824_i140147520992400.inputs4"],
          ["self.in0_cim_stencil.1","i140147531536336_i140147520054672.inputs0"],
          ["self.in0_cim_stencil.7","i140147531536336_i140147520054672.inputs1"],
          ["self.in0_cim_stencil.1","i140147531536464_i140147520054672.inputs0"],
          ["self.in0_cim_stencil.6","i140147531536464_i140147520054672.inputs1"]
        ]
      },
      "hcompute_cim_stencil":{
        "type":["Record",[
          ["in0_lgxx_stencil",["Array",1,["Array",16,"BitIn"]]],
          ["in1_lgxy_stencil",["Array",1,["Array",16,"BitIn"]]],
          ["in2_lgyy_stencil",["Array",1,["Array",16,"BitIn"]]],
          ["out_cim_stencil",["Array",16,"Bit"]]
        ]],
        "instances":{
          "c140147520274832":{
            "modref":"corebit.const",
            "modargs":{"value":["Bool",true]}
          },
          "c140147520276368":{
            "genref":"coreir.const",
            "genargs":{"width":["Int",55]},
            "modargs":{"value":[["BitVector",55],"55'h00209ffff5294a"]}
          },
          "c140147520276624":{
            "genref":"coreir.const",
            "genargs":{"width":["Int",55]},
            "modargs":{"value":[["BitVector",55],"55'h00000000000000"]}
          },
          "c140147520277584":{
            "modref":"corebit.const",
            "modargs":{"value":["Bool",true]}
          },
          "c140147520277840":{
            "modref":"corebit.const",
            "modargs":{"value":["Bool",true]}
          },
          "c140147520309200":{
            "modref":"corebit.const",
            "modargs":{"value":["Bool",true]}
          },
          "c140147520309264":{
            "genref":"coreir.const",
            "genargs":{"width":["Int",55]},
            "modargs":{"value":[["BitVector",55],"55'h0000200065294a"]}
          },
          "c140147520309840":{
            "genref":"coreir.const",
            "genargs":{"width":["Int",55]},
            "modargs":{"value":[["BitVector",55],"55'h002060000518c5"]}
          },
          "c140147520309904":{
            "modref":"corebit.const",
            "modargs":{"value":["Bool",true]}
          },
          "c140147520311184":{
            "modref":"corebit.const",
            "modargs":{"value":["Bool",true]}
          },
          "c140147520667856":{
            "modref":"corebit.const",
            "modargs":{"value":["Bool",true]}
          },
          "c140147520669200":{
            "modref":"corebit.const",
            "modargs":{"value":["Bool",true]}
          },
          "c140147520671632":{
            "modref":"corebit.const",
            "modargs":{"value":["Bool",true]}
          },
          "c140147520720976":{
            "genref":"coreir.const",
            "genargs":{"width":["Int",55]},
            "modargs":{"value":[["BitVector",55],"55'h0000200065294a"]}
          },
          "c140147520722512":{
            "genref":"coreir.const",
            "genargs":{"width":["Int",55]},
            "modargs":{"value":[["BitVector",55],"55'h002060000518c5"]}
          },
          "c140147526712848":{
            "genref":"coreir.const",
            "genargs":{"width":["Int",55]},
            "modargs":{"value":[["BitVector",55],"55'h0000200045294a"]}
          },
          "c140147526732176":{
            "genref":"coreir.const",
            "genargs":{"width":["Int",55]},
            "modargs":{"value":[["BitVector",55],"55'h002060000518c5"]}
          },
          "c140147534064272":{
            "genref":"coreir.const",
            "genargs":{"width":["Int",55]},
            "modargs":{"value":[["BitVector",55],"55'h002060000518c5"]}
          },
          "c140147534942416":{
            "modref":"corebit.const",
            "modargs":{"value":["Bool",true]}
          },
          "c140147537047632":{
            "genref":"coreir.const",
            "genargs":{"width":["Int",55]},
            "modargs":{"value":[["BitVector",55],"55'h0000200065294a"]}
          },
          "c140147537072208":{
            "modref":"corebit.const",
            "modargs":{"value":["Bool",true]}
          },
          "c140147537072656":{
            "modref":"corebit.const",
            "modargs":{"value":["Bool",true]}
          },
          "c140147537074832":{
            "genref":"coreir.const",
            "genargs":{"width":["Int",55]},
            "modargs":{"value":[["BitVector",55],"55'h00000000000000"]}
          },
          "c140147537075216":{
            "modref":"corebit.const",
            "modargs":{"value":["Bool",true]}
          },
          "c140147538410768":{
            "genref":"coreir.const",
            "genargs":{"width":["Int",55]},
            "modargs":{"value":[["BitVector",55],"55'h00209ffff5294a"]}
          },
          "c140147544356048":{
            "modref":"corebit.const",
            "modargs":{"value":["Bool",true]}
          },
          "c140147544357712":{
            "genref":"coreir.const",
            "genargs":{"width":["Int",55]},
            "modargs":{"value":[["BitVector",55],"55'h00208ffff5294a"]}
          },
          "c140147544358416":{
            "genref":"coreir.const",
            "genargs":{"width":["Int",55]},
            "modargs":{"value":[["BitVector",55],"55'h00000000000000"]}
          },
          "i140147515940240_i140147545185680":{
            "modref":"global.PE"
          },
          "i140147517994192_i140147536569552":{
            "modref":"global.PE"
          },
          "i140147531457040_i140147520043280":{
            "modref":"global.PE"
          },
          "i140147531457872_i140147520043280":{
            "modref":"global.PE"
          },
          "i140147531459536_i140147520043280":{
            "modref":"global.PE"
          },
          "i140147531460240_i140147520043280":{
            "modref":"global.PE"
          },
          "i140147531481040_i140147545185680":{
            "modref":"global.PE"
          },
          "i140147534029968_i140147536569552":{
            "modref":"global.PE"
          },
          "i140147534259216_i140147515472400":{
            "modref":"global.PE"
          },
          "i140147534260240_i140147515472400":{
            "modref":"global.PE"
          },
          "i140147536968720_i140147545185680":{
            "modref":"global.PE"
          },
          "i140147544465680_i140147545185680":{
            "modref":"global.PE"
          },
          "i140147544469328_i140147536569552":{
            "modref":"global.PE"
          },
          "i140147545869136_i140147547023440":{
            "modref":"global.PE"
          }
        },
        "connections":[
          ["i140147534029968_i140147536569552.clk_en","c140147520274832.out"],
          ["i140147534260240_i140147515472400.inst","c140147520276368.out"],
          ["i140147544469328_i140147536569552.inst","c140147520276624.out"],
          ["i140147545869136_i140147547023440.clk_en","c140147520277584.out"],
          ["i140147531481040_i140147545185680.clk_en","c140147520277840.out"],
          ["i140147536968720_i140147545185680.clk_en","c140147520309200.out"],
          ["i140147531459536_i140147520043280.inst","c140147520309264.out"],
          ["i140147536968720_i140147545185680.inst","c140147520309840.out"],
          ["i140147515940240_i140147545185680.clk_en","c140147520309904.out"],
          ["i140147531459536_i140147520043280.clk_en","c140147520311184.out"],
          ["i140147531457040_i140147520043280.clk_en","c140147520667856.out"],
          ["i140147544465680_i140147545185680.clk_en","c140147520669200.out"],
          ["i140147544469328_i140147536569552.clk_en","c140147520671632.out"],
          ["i140147531457040_i140147520043280.inst","c140147520720976.out"],
          ["i140147544465680_i140147545185680.inst","c140147520722512.out"],
          ["i140147531460240_i140147520043280.inst","c140147526712848.out"],
          ["i140147531481040_i140147545185680.inst","c140147526732176.out"],
          ["i140147515940240_i140147545185680.inst","c140147534064272.out"],
          ["i140147531457872_i140147520043280.clk_en","c140147534942416.out"],
          ["i140147531457872_i140147520043280.inst","c140147537047632.out"],
          ["i140147534259216_i140147515472400.clk_en","c140147537072208.out"],
          ["i140147534260240_i140147515472400.clk_en","c140147537072656.out"],
          ["i140147517994192_i140147536569552.inst","c140147537074832.out"],
          ["i140147517994192_i140147536569552.clk_en","c140147537075216.out"],
          ["i140147534259216_i140147515472400.inst","c140147538410768.out"],
          ["i140147531460240_i140147520043280.clk_en","c140147544356048.out"],
          ["i140147545869136_i140147547023440.inst","c140147544357712.out"],
          ["i140147534029968_i140147536569552.inst","c140147544358416.out"],
          ["i140147517994192_i140147536569552.inputs0","i140147515940240_i140147545185680.O0"],
          ["i140147545869136_i140147547023440.inputs0","i140147515940240_i140147545185680.O0"],
          ["i140147531457872_i140147520043280.O0","i140147515940240_i140147545185680.inputs0"],
          ["self.in2_lgyy_stencil.0","i140147515940240_i140147545185680.inputs1"],
          ["i140147534260240_i140147515472400.inputs1","i140147517994192_i140147536569552.O0"],
          ["i140147536968720_i140147545185680.O0","i140147517994192_i140147536569552.inputs1"],
          ["i140147544465680_i140147545185680.inputs0","i140147531457040_i140147520043280.O0"],
          ["i140147536968720_i140147545185680.inputs0","i140147531459536_i140147520043280.O0"],
          ["i140147531481040_i140147545185680.inputs0","i140147531460240_i140147520043280.O0"],
          ["i140147534259216_i140147515472400.inputs0","i140147531481040_i140147545185680.O0"],
          ["i140147534029968_i140147536569552.O0","i140147531481040_i140147545185680.inputs1"],
          ["i140147545869136_i140147547023440.O0","i140147534029968_i140147536569552.inputs0"],
          ["i140147545869136_i140147547023440.O0","i140147534029968_i140147536569552.inputs1"],
          ["self.out_cim_stencil","i140147534259216_i140147515472400.O0"],
          ["i140147534260240_i140147515472400.O0","i140147534259216_i140147515472400.inputs1"],
          ["i140147544469328_i140147536569552.O0","i140147534260240_i140147515472400.inputs0"],
          ["i140147545869136_i140147547023440.inputs1","i140147536968720_i140147545185680.O0"],
          ["self.in0_lgxx_stencil.0","i140147536968720_i140147545185680.inputs1"],
          ["i140147544469328_i140147536569552.inputs0","i140147544465680_i140147545185680.O0"],
          ["i140147544469328_i140147536569552.inputs1","i140147544465680_i140147545185680.O0"],
          ["self.in1_lgxy_stencil.0","i140147544465680_i140147545185680.inputs1"]
        ]
      },
      "hcompute_grad_x_unclamp_stencil_1":{
        "type":["Record",[
          ["in0_grad_x_unclamp_stencil",["Array",1,["Array",16,"BitIn"]]],
          ["in1_padded16_global_wrapper_stencil",["Array",6,["Array",16,"BitIn"]]],
          ["out_grad_x_unclamp_stencil",["Array",16,"Bit"]]
        ]],
        "instances":{
          "c140147517167120":{
            "genref":"coreir.const",
            "genargs":{"width":["Int",55]},
            "modargs":{"value":[["BitVector",55],"55'h00209ffff5294a"]}
          },
          "c140147517196048":{
            "genref":"coreir.const",
            "genargs":{"width":["Int",55]},
            "modargs":{"value":[["BitVector",55],"55'h00000000000000"]}
          },
          "c140147517196304":{
            "modref":"corebit.const",
            "modargs":{"value":["Bool",true]}
          },
          "c140147517196560":{
            "modref":"corebit.const",
            "modargs":{"value":["Bool",true]}
          },
          "c140147517196624":{
            "genref":"coreir.const",
            "genargs":{"width":["Int",55]},
            "modargs":{"value":[["BitVector",55],"55'h0000200025294a"]}
          },
          "c140147517196880":{
            "genref":"coreir.const",
            "genargs":{"width":["Int",55]},
            "modargs":{"value":[["BitVector",55],"55'h00208ffff5294a"]}
          },
          "c140147517197008":{
            "genref":"coreir.const",
            "genargs":{"width":["Int",55]},
            "modargs":{"value":[["BitVector",55],"55'h00209ffff5294a"]}
          },
          "c140147517248144":{
            "genref":"coreir.const",
            "genargs":{"width":["Int",55]},
            "modargs":{"value":[["BitVector",55],"55'h00208ffff5294a"]}
          },
          "c140147517248208":{
            "genref":"coreir.const",
            "genargs":{"width":["Int",55]},
            "modargs":{"value":[["BitVector",55],"55'h00208ffff5294a"]}
          },
          "c140147517248400":{
            "modref":"corebit.const",
            "modargs":{"value":["Bool",true]}
          },
          "c140147517248464":{
            "modref":"corebit.const",
            "modargs":{"value":["Bool",true]}
          },
          "c140147517248976":{
            "modref":"corebit.const",
            "modargs":{"value":["Bool",true]}
          },
          "c140147517249616":{
            "genref":"coreir.const",
            "genargs":{"width":["Int",55]},
            "modargs":{"value":[["BitVector",55],"55'h0000200025294a"]}
          },
          "c140147517250128":{
            "modref":"corebit.const",
            "modargs":{"value":["Bool",true]}
          },
          "c140147517250192":{
            "modref":"corebit.const",
            "modargs":{"value":["Bool",true]}
          },
          "c140147517250384":{
            "modref":"corebit.const",
            "modargs":{"value":["Bool",true]}
          },
          "c140147517251088":{
            "modref":"corebit.const",
            "modargs":{"value":["Bool",true]}
          },
          "c140147517251344":{
            "modref":"corebit.const",
            "modargs":{"value":["Bool",true]}
          },
          "c140147517251536":{
            "genref":"coreir.const",
            "genargs":{"width":["Int",55]},
            "modargs":{"value":[["BitVector",55],"55'h00000000000000"]}
          },
          "c140147517605072":{
            "genref":"coreir.const",
            "genargs":{"width":["Int",55]},
            "modargs":{"value":[["BitVector",55],"55'h00209ffff5294a"]}
          },
          "i140147516509328_i140147520043280":{
            "modref":"global.PE"
          },
          "i140147516509392_i140147520043280":{
            "modref":"global.PE"
          },
          "i140147516571856_i140147547023440":{
            "modref":"global.PE"
          },
          "i140147516572240_i140147515472400":{
            "modref":"global.PE"
          },
          "i140147516573008_i140147536569552":{
            "modref":"global.PE"
          },
          "i140147516573712_i140147547023440":{
            "modref":"global.PE"
          },
          "i140147516573904_i140147515472400":{
            "modref":"global.PE"
          },
          "i140147516574160_i140147515472400":{
            "modref":"global.PE"
          },
          "i140147516575184_i140147547023440":{
            "modref":"global.PE"
          },
          "i140147516575312_i140147536569552":{
            "modref":"global.PE"
          }
        },
        "connections":[
          ["i140147516574160_i140147515472400.inst","c140147517167120.out"],
          ["i140147516575312_i140147536569552.inst","c140147517196048.out"],
          ["i140147516575312_i140147536569552.clk_en","c140147517196304.out"],
          ["i140147516509392_i140147520043280.clk_en","c140147517196560.out"],
          ["i140147516509392_i140147520043280.inst","c140147517196624.out"],
          ["i140147516573712_i140147547023440.inst","c140147517196880.out"],
          ["i140147516572240_i140147515472400.inst","c140147517197008.out"],
          ["i140147516571856_i140147547023440.inst","c140147517248144.out"],
          ["i140147516575184_i140147547023440.inst","c140147517248208.out"],
          ["i140147516573904_i140147515472400.clk_en","c140147517248400.out"],
          ["i140147516509328_i140147520043280.clk_en","c140147517248464.out"],
          ["i140147516571856_i140147547023440.clk_en","c140147517248976.out"],
          ["i140147516509328_i140147520043280.inst","c140147517249616.out"],
          ["i140147516573712_i140147547023440.clk_en","c140147517250128.out"],
          ["i140147516572240_i140147515472400.clk_en","c140147517250192.out"],
          ["i140147516574160_i140147515472400.clk_en","c140147517250384.out"],
          ["i140147516573008_i140147536569552.clk_en","c140147517251088.out"],
          ["i140147516575184_i140147547023440.clk_en","c140147517251344.out"],
          ["i140147516573008_i140147536569552.inst","c140147517251536.out"],
          ["i140147516573904_i140147515472400.inst","c140147517605072.out"],
          ["i140147516573008_i140147536569552.inputs0","i140147516509328_i140147520043280.O0"],
          ["i140147516575312_i140147536569552.inputs0","i140147516509392_i140147520043280.O0"],
          ["i140147516573712_i140147547023440.inputs0","i140147516571856_i140147547023440.O0"],
          ["i140147516575184_i140147547023440.O0","i140147516571856_i140147547023440.inputs0"],
          ["self.in1_padded16_global_wrapper_stencil.0","i140147516571856_i140147547023440.inputs1"],
          ["i140147516574160_i140147515472400.inputs1","i140147516572240_i140147515472400.O0"],
          ["self.in1_padded16_global_wrapper_stencil.3","i140147516572240_i140147515472400.inputs0"],
          ["i140147516573712_i140147547023440.O0","i140147516572240_i140147515472400.inputs1"],
          ["i140147516575184_i140147547023440.inputs0","i140147516573008_i140147536569552.O0"],
          ["self.in1_padded16_global_wrapper_stencil.2","i140147516573008_i140147536569552.inputs1"],
          ["self.in0_grad_x_unclamp_stencil.0","i140147516573712_i140147547023440.inputs1"],
          ["self.out_grad_x_unclamp_stencil","i140147516573904_i140147515472400.O0"],
          ["self.in1_padded16_global_wrapper_stencil.5","i140147516573904_i140147515472400.inputs0"],
          ["i140147516574160_i140147515472400.O0","i140147516573904_i140147515472400.inputs1"],
          ["i140147516575312_i140147536569552.O0","i140147516574160_i140147515472400.inputs0"],
          ["self.in1_padded16_global_wrapper_stencil.1","i140147516575184_i140147547023440.inputs1"],
          ["self.in1_padded16_global_wrapper_stencil.4","i140147516575312_i140147536569552.inputs1"]
        ]
      },
      "hcompute_grad_x_unclamp_stencil":{
        "type":["Record",[
          ["out_grad_x_unclamp_stencil",["Array",16,"Bit"]]
        ]],
        "instances":{
          "c140147516465552":{
            "genref":"coreir.const",
            "genargs":{"width":["Int",55]},
            "modargs":{"value":[["BitVector",55],"55'h0000200005294a"]}
          },
          "c140147516466512":{
            "modref":"corebit.const",
            "modargs":{"value":["Bool",true]}
          },
          "i140147526918416_i140147520043280":{
            "modref":"global.PE"
          }
        },
        "connections":[
          ["i140147526918416_i140147520043280.inst","c140147516465552.out"],
          ["i140147526918416_i140147520043280.clk_en","c140147516466512.out"],
          ["self.out_grad_x_unclamp_stencil","i140147526918416_i140147520043280.O0"]
        ]
      },
      "hcompute_grad_y_unclamp_stencil_1":{
        "type":["Record",[
          ["in0_grad_y_unclamp_stencil",["Array",1,["Array",16,"BitIn"]]],
          ["in1_padded16_global_wrapper_stencil",["Array",6,["Array",16,"BitIn"]]],
          ["out_grad_y_unclamp_stencil",["Array",16,"Bit"]]
        ]],
        "instances":{
          "c140147517974864":{
            "genref":"coreir.const",
            "genargs":{"width":["Int",55]},
            "modargs":{"value":[["BitVector",55],"55'h00208ffff5294a"]}
          },
          "c140147531096848":{
            "genref":"coreir.const",
            "genargs":{"width":["Int",55]},
            "modargs":{"value":[["BitVector",55],"55'h0000200025294a"]}
          },
          "c140147531097424":{
            "genref":"coreir.const",
            "genargs":{"width":["Int",55]},
            "modargs":{"value":[["BitVector",55],"55'h00000000000000"]}
          },
          "c140147531099984":{
            "genref":"coreir.const",
            "genargs":{"width":["Int",55]},
            "modargs":{"value":[["BitVector",55],"55'h00209ffff5294a"]}
          },
          "c140147531104784":{
            "modref":"corebit.const",
            "modargs":{"value":["Bool",true]}
          },
          "c140147531105872":{
            "genref":"coreir.const",
            "genargs":{"width":["Int",55]},
            "modargs":{"value":[["BitVector",55],"55'h00000000000000"]}
          },
          "c140147531106640":{
            "genref":"coreir.const",
            "genargs":{"width":["Int",55]},
            "modargs":{"value":[["BitVector",55],"55'h0000200025294a"]}
          },
          "c140147532033360":{
            "genref":"coreir.const",
            "genargs":{"width":["Int",55]},
            "modargs":{"value":[["BitVector",55],"55'h00209ffff5294a"]}
          },
          "c140147534112080":{
            "genref":"coreir.const",
            "genargs":{"width":["Int",55]},
            "modargs":{"value":[["BitVector",55],"55'h00208ffff5294a"]}
          },
          "c140147537665488":{
            "genref":"coreir.const",
            "genargs":{"width":["Int",55]},
            "modargs":{"value":[["BitVector",55],"55'h00209ffff5294a"]}
          },
          "c140147544432848":{
            "modref":"corebit.const",
            "modargs":{"value":["Bool",true]}
          },
          "c140147544433104":{
            "modref":"corebit.const",
            "modargs":{"value":["Bool",true]}
          },
          "c140147544433424":{
            "modref":"corebit.const",
            "modargs":{"value":["Bool",true]}
          },
          "c140147544433552":{
            "modref":"corebit.const",
            "modargs":{"value":["Bool",true]}
          },
          "c140147544433680":{
            "modref":"corebit.const",
            "modargs":{"value":["Bool",true]}
          },
          "c140147544434640":{
            "modref":"corebit.const",
            "modargs":{"value":["Bool",true]}
          },
          "c140147544436688":{
            "modref":"corebit.const",
            "modargs":{"value":["Bool",true]}
          },
          "c140147548874512":{
            "modref":"corebit.const",
            "modargs":{"value":["Bool",true]}
          },
          "c140147548875152":{
            "modref":"corebit.const",
            "modargs":{"value":["Bool",true]}
          },
          "c140147549926288":{
            "genref":"coreir.const",
            "genargs":{"width":["Int",55]},
            "modargs":{"value":[["BitVector",55],"55'h00208ffff5294a"]}
          },
          "i140147516432848_i140147547023440":{
            "modref":"global.PE"
          },
          "i140147516432976_i140147547023440":{
            "modref":"global.PE"
          },
          "i140147516434256_i140147547023440":{
            "modref":"global.PE"
          },
          "i140147516436304_i140147536569552":{
            "modref":"global.PE"
          },
          "i140147520840080_i140147536569552":{
            "modref":"global.PE"
          },
          "i140147520841296_i140147515472400":{
            "modref":"global.PE"
          },
          "i140147521290768_i140147515472400":{
            "modref":"global.PE"
          },
          "i140147521292176_i140147520043280":{
            "modref":"global.PE"
          },
          "i140147521292688_i140147520043280":{
            "modref":"global.PE"
          },
          "i140147547023952_i140147515472400":{
            "modref":"global.PE"
          }
        },
        "connections":[
          ["i140147516432848_i140147547023440.inst","c140147517974864.out"],
          ["i140147521292688_i140147520043280.inst","c140147531096848.out"],
          ["i140147520840080_i140147536569552.inst","c140147531097424.out"],
          ["i140147520841296_i140147515472400.inst","c140147531099984.out"],
          ["i140147521292176_i140147520043280.clk_en","c140147531104784.out"],
          ["i140147516436304_i140147536569552.inst","c140147531105872.out"],
          ["i140147521292176_i140147520043280.inst","c140147531106640.out"],
          ["i140147547023952_i140147515472400.inst","c140147532033360.out"],
          ["i140147516434256_i140147547023440.inst","c140147534112080.out"],
          ["i140147521290768_i140147515472400.inst","c140147537665488.out"],
          ["i140147521290768_i140147515472400.clk_en","c140147544432848.out"],
          ["i140147547023952_i140147515472400.clk_en","c140147544433104.out"],
          ["i140147516436304_i140147536569552.clk_en","c140147544433424.out"],
          ["i140147520841296_i140147515472400.clk_en","c140147544433552.out"],
          ["i140147516432848_i140147547023440.clk_en","c140147544433680.out"],
          ["i140147516432976_i140147547023440.clk_en","c140147544434640.out"],
          ["i140147516434256_i140147547023440.clk_en","c140147544436688.out"],
          ["i140147520840080_i140147536569552.clk_en","c140147548874512.out"],
          ["i140147521292688_i140147520043280.clk_en","c140147548875152.out"],
          ["i140147516432976_i140147547023440.inst","c140147549926288.out"],
          ["i140147516432976_i140147547023440.inputs0","i140147516432848_i140147547023440.O0"],
          ["i140147516436304_i140147536569552.O0","i140147516432848_i140147547023440.inputs0"],
          ["self.in1_padded16_global_wrapper_stencil.4","i140147516432848_i140147547023440.inputs1"],
          ["i140147516434256_i140147547023440.inputs0","i140147516432976_i140147547023440.O0"],
          ["self.in1_padded16_global_wrapper_stencil.3","i140147516432976_i140147547023440.inputs1"],
          ["i140147547023952_i140147515472400.inputs1","i140147516434256_i140147547023440.O0"],
          ["self.in0_grad_y_unclamp_stencil.0","i140147516434256_i140147547023440.inputs1"],
          ["i140147521292176_i140147520043280.O0","i140147516436304_i140147536569552.inputs0"],
          ["self.in1_padded16_global_wrapper_stencil.5","i140147516436304_i140147536569552.inputs1"],
          ["i140147520841296_i140147515472400.inputs0","i140147520840080_i140147536569552.O0"],
          ["i140147521292688_i140147520043280.O0","i140147520840080_i140147536569552.inputs0"],
          ["self.in1_padded16_global_wrapper_stencil.1","i140147520840080_i140147536569552.inputs1"],
          ["i140147521290768_i140147515472400.inputs1","i140147520841296_i140147515472400.O0"],
          ["i140147547023952_i140147515472400.O0","i140147520841296_i140147515472400.inputs1"],
          ["self.out_grad_y_unclamp_stencil","i140147521290768_i140147515472400.O0"],
          ["self.in1_padded16_global_wrapper_stencil.2","i140147521290768_i140147515472400.inputs0"],
          ["self.in1_padded16_global_wrapper_stencil.0","i140147547023952_i140147515472400.inputs0"]
        ]
      },
      "hcompute_grad_y_unclamp_stencil":{
        "type":["Record",[
          ["out_grad_y_unclamp_stencil",["Array",16,"Bit"]]
        ]],
        "instances":{
          "c140147516401680":{
            "genref":"coreir.const",
            "genargs":{"width":["Int",55]},
            "modargs":{"value":[["BitVector",55],"55'h0000200005294a"]}
          },
          "c140147516403536":{
            "modref":"corebit.const",
            "modargs":{"value":["Bool",true]}
          },
          "i140147516623440_i140147520043280":{
            "modref":"global.PE"
          }
        },
        "connections":[
          ["i140147516623440_i140147520043280.inst","c140147516401680.out"],
          ["i140147516623440_i140147520043280.clk_en","c140147516403536.out"],
          ["self.out_grad_y_unclamp_stencil","i140147516623440_i140147520043280.O0"]
        ]
      },
      "hcompute_hw_output_stencil":{
        "type":["Record",[
          ["in0_cim_output_stencil",["Array",1,["Array",16,"BitIn"]]],
          ["out_hw_output_stencil",["Array",16,"Bit"]]
        ]],
        "connections":[
          ["self.out_hw_output_stencil","self.in0_cim_output_stencil.0"]
        ]
      },
      "hcompute_lgxx_stencil_1":{
        "type":["Record",[
          ["in0_lgxx_stencil",["Array",1,["Array",16,"BitIn"]]],
          ["in1_lxx_stencil",["Array",9,["Array",16,"BitIn"]]],
          ["out_lgxx_stencil",["Array",16,"Bit"]]
        ]],
        "instances":{
          "c140147519529040":{
            "genref":"coreir.const",
            "genargs":{"width":["Int",55]},
            "modargs":{"value":[["BitVector",55],"55'h00208ffff5294a"]}
          },
          "c140147519618384":{
            "genref":"coreir.const",
            "genargs":{"width":["Int",55]},
            "modargs":{"value":[["BitVector",55],"55'h00208ffff5294a"]}
          },
          "c140147519618512":{
            "genref":"coreir.const",
            "genargs":{"width":["Int",55]},
            "modargs":{"value":[["BitVector",55],"55'h00208ffff5294a"]}
          },
          "c140147519618832":{
            "genref":"coreir.const",
            "genargs":{"width":["Int",55]},
            "modargs":{"value":[["BitVector",55],"55'h00208ffff5294a"]}
          },
          "c140147519618960":{
            "genref":"coreir.const",
            "genargs":{"width":["Int",55]},
            "modargs":{"value":[["BitVector",55],"55'h00208ffff5294a"]}
          },
          "c140147519644048":{
            "modref":"corebit.const",
            "modargs":{"value":["Bool",true]}
          },
          "c140147519644240":{
            "modref":"corebit.const",
            "modargs":{"value":["Bool",true]}
          },
          "c140147519644432":{
            "modref":"corebit.const",
            "modargs":{"value":["Bool",true]}
          },
          "c140147519644624":{
            "modref":"corebit.const",
            "modargs":{"value":["Bool",true]}
          },
          "c140147519644816":{
            "modref":"corebit.const",
            "modargs":{"value":["Bool",true]}
          },
          "c140147519645008":{
            "modref":"corebit.const",
            "modargs":{"value":["Bool",true]}
          },
          "c140147519645200":{
            "modref":"corebit.const",
            "modargs":{"value":["Bool",true]}
          },
          "c140147519645520":{
            "modref":"corebit.const",
            "modargs":{"value":["Bool",true]}
          },
          "c140147519645712":{
            "modref":"corebit.const",
            "modargs":{"value":["Bool",true]}
          },
          "c140147521262096":{
            "genref":"coreir.const",
            "genargs":{"width":["Int",55]},
            "modargs":{"value":[["BitVector",55],"55'h00208ffff5294a"]}
          },
          "c140147521265296":{
            "genref":"coreir.const",
            "genargs":{"width":["Int",55]},
            "modargs":{"value":[["BitVector",55],"55'h00208ffff5294a"]}
          },
          "c140147521265488":{
            "genref":"coreir.const",
            "genargs":{"width":["Int",55]},
            "modargs":{"value":[["BitVector",55],"55'h00208ffff5294a"]}
          },
          "c140147533135440":{
            "genref":"coreir.const",
            "genargs":{"width":["Int",55]},
            "modargs":{"value":[["BitVector",55],"55'h00208ffff5294a"]}
          },
          "i140147544510224_i140147547023440":{
            "modref":"global.PE"
          },
          "i140147545041424_i140147547023440":{
            "modref":"global.PE"
          },
          "i140147545330000_i140147547023440":{
            "modref":"global.PE"
          },
          "i140147545332176_i140147547023440":{
            "modref":"global.PE"
          },
          "i140147545444944_i140147547023440":{
            "modref":"global.PE"
          },
          "i140147545446800_i140147547023440":{
            "modref":"global.PE"
          },
          "i140147545446992_i140147547023440":{
            "modref":"global.PE"
          },
          "i140147545447248_i140147547023440":{
            "modref":"global.PE"
          },
          "i140147545447376_i140147547023440":{
            "modref":"global.PE"
          }
        },
        "connections":[
          ["i140147545447248_i140147547023440.inst","c140147519529040.out"],
          ["i140147545332176_i140147547023440.inst","c140147519618384.out"],
          ["i140147545446992_i140147547023440.inst","c140147519618512.out"],
          ["i140147545447376_i140147547023440.inst","c140147519618832.out"],
          ["i140147545446800_i140147547023440.inst","c140147519618960.out"],
          ["i140147545447376_i140147547023440.clk_en","c140147519644048.out"],
          ["i140147545446992_i140147547023440.clk_en","c140147519644240.out"],
          ["i140147545446800_i140147547023440.clk_en","c140147519644432.out"],
          ["i140147545332176_i140147547023440.clk_en","c140147519644624.out"],
          ["i140147545330000_i140147547023440.clk_en","c140147519644816.out"],
          ["i140147544510224_i140147547023440.clk_en","c140147519645008.out"],
          ["i140147545041424_i140147547023440.clk_en","c140147519645200.out"],
          ["i140147545444944_i140147547023440.clk_en","c140147519645520.out"],
          ["i140147545447248_i140147547023440.clk_en","c140147519645712.out"],
          ["i140147545041424_i140147547023440.inst","c140147521262096.out"],
          ["i140147545330000_i140147547023440.inst","c140147521265296.out"],
          ["i140147544510224_i140147547023440.inst","c140147521265488.out"],
          ["i140147545444944_i140147547023440.inst","c140147533135440.out"],
          ["i140147545041424_i140147547023440.inputs0","i140147544510224_i140147547023440.O0"],
          ["i140147545330000_i140147547023440.O0","i140147544510224_i140147547023440.inputs0"],
          ["self.in1_lxx_stencil.2","i140147544510224_i140147547023440.inputs1"],
          ["i140147545444944_i140147547023440.inputs0","i140147545041424_i140147547023440.O0"],
          ["self.in1_lxx_stencil.1","i140147545041424_i140147547023440.inputs1"],
          ["i140147545332176_i140147547023440.O0","i140147545330000_i140147547023440.inputs0"],
          ["self.in1_lxx_stencil.3","i140147545330000_i140147547023440.inputs1"],
          ["i140147545446800_i140147547023440.O0","i140147545332176_i140147547023440.inputs0"],
          ["self.in1_lxx_stencil.4","i140147545332176_i140147547023440.inputs1"],
          ["i140147545447248_i140147547023440.inputs0","i140147545444944_i140147547023440.O0"],
          ["self.in0_lgxx_stencil.0","i140147545444944_i140147547023440.inputs1"],
          ["i140147545446992_i140147547023440.O0","i140147545446800_i140147547023440.inputs0"],
          ["self.in1_lxx_stencil.5","i140147545446800_i140147547023440.inputs1"],
          ["i140147545447376_i140147547023440.O0","i140147545446992_i140147547023440.inputs0"],
          ["self.in1_lxx_stencil.6","i140147545446992_i140147547023440.inputs1"],
          ["self.out_lgxx_stencil","i140147545447248_i140147547023440.O0"],
          ["self.in1_lxx_stencil.0","i140147545447248_i140147547023440.inputs1"],
          ["self.in1_lxx_stencil.8","i140147545447376_i140147547023440.inputs0"],
          ["self.in1_lxx_stencil.7","i140147545447376_i140147547023440.inputs1"]
        ]
      },
      "hcompute_lgxx_stencil":{
        "type":["Record",[
          ["out_lgxx_stencil",["Array",16,"Bit"]]
        ]],
        "instances":{
          "c140147544818768":{
            "genref":"coreir.const",
            "genargs":{"width":["Int",55]},
            "modargs":{"value":[["BitVector",55],"55'h0000200005294a"]}
          },
          "c140147544963408":{
            "modref":"corebit.const",
            "modargs":{"value":["Bool",true]}
          },
          "i140147521226000_i140147520043280":{
            "modref":"global.PE"
          }
        },
        "connections":[
          ["i140147521226000_i140147520043280.inst","c140147544818768.out"],
          ["i140147521226000_i140147520043280.clk_en","c140147544963408.out"],
          ["self.out_lgxx_stencil","i140147521226000_i140147520043280.O0"]
        ]
      },
      "hcompute_lgxy_stencil_1":{
        "type":["Record",[
          ["in0_lgxy_stencil",["Array",1,["Array",16,"BitIn"]]],
          ["in1_lxy_stencil",["Array",9,["Array",16,"BitIn"]]],
          ["out_lgxy_stencil",["Array",16,"Bit"]]
        ]],
        "instances":{
          "c140147471447888":{
            "genref":"coreir.const",
            "genargs":{"width":["Int",55]},
            "modargs":{"value":[["BitVector",55],"55'h00208ffff5294a"]}
          },
          "c140147471448464":{
            "genref":"coreir.const",
            "genargs":{"width":["Int",55]},
            "modargs":{"value":[["BitVector",55],"55'h00208ffff5294a"]}
          },
          "c140147471454864":{
            "genref":"coreir.const",
            "genargs":{"width":["Int",55]},
            "modargs":{"value":[["BitVector",55],"55'h00208ffff5294a"]}
          },
          "c140147471456208":{
            "genref":"coreir.const",
            "genargs":{"width":["Int",55]},
            "modargs":{"value":[["BitVector",55],"55'h00208ffff5294a"]}
          },
          "c140147471458256":{
            "genref":"coreir.const",
            "genargs":{"width":["Int",55]},
            "modargs":{"value":[["BitVector",55],"55'h00208ffff5294a"]}
          },
          "c140147471485712":{
            "genref":"coreir.const",
            "genargs":{"width":["Int",55]},
            "modargs":{"value":[["BitVector",55],"55'h00208ffff5294a"]}
          },
          "c140147471486224":{
            "genref":"coreir.const",
            "genargs":{"width":["Int",55]},
            "modargs":{"value":[["BitVector",55],"55'h00208ffff5294a"]}
          },
          "c140147471486288":{
            "genref":"coreir.const",
            "genargs":{"width":["Int",55]},
            "modargs":{"value":[["BitVector",55],"55'h00208ffff5294a"]}
          },
          "c140147471524048":{
            "genref":"coreir.const",
            "genargs":{"width":["Int",55]},
            "modargs":{"value":[["BitVector",55],"55'h00208ffff5294a"]}
          },
          "c140147471524688":{
            "modref":"corebit.const",
            "modargs":{"value":["Bool",true]}
          },
          "c140147471524880":{
            "modref":"corebit.const",
            "modargs":{"value":["Bool",true]}
          },
          "c140147471525072":{
            "modref":"corebit.const",
            "modargs":{"value":["Bool",true]}
          },
          "c140147471525264":{
            "modref":"corebit.const",
            "modargs":{"value":["Bool",true]}
          },
          "c140147471525456":{
            "modref":"corebit.const",
            "modargs":{"value":["Bool",true]}
          },
          "c140147471525648":{
            "modref":"corebit.const",
            "modargs":{"value":["Bool",true]}
          },
          "c140147471525840":{
            "modref":"corebit.const",
            "modargs":{"value":["Bool",true]}
          },
          "c140147471526160":{
            "modref":"corebit.const",
            "modargs":{"value":["Bool",true]}
          },
          "c140147471526352":{
            "modref":"corebit.const",
            "modargs":{"value":["Bool",true]}
          },
          "i140147472251600_i140147547023440":{
            "modref":"global.PE"
          },
          "i140147472252176_i140147547023440":{
            "modref":"global.PE"
          },
          "i140147472294864_i140147547023440":{
            "modref":"global.PE"
          },
          "i140147472295312_i140147547023440":{
            "modref":"global.PE"
          },
          "i140147472295376_i140147547023440":{
            "modref":"global.PE"
          },
          "i140147472295696_i140147547023440":{
            "modref":"global.PE"
          },
          "i140147472296528_i140147547023440":{
            "modref":"global.PE"
          },
          "i140147472297360_i140147547023440":{
            "modref":"global.PE"
          },
          "i140147472297808_i140147547023440":{
            "modref":"global.PE"
          }
        },
        "connections":[
          ["i140147472295312_i140147547023440.inst","c140147471447888.out"],
          ["i140147472294864_i140147547023440.inst","c140147471448464.out"],
          ["i140147472295376_i140147547023440.inst","c140147471454864.out"],
          ["i140147472251600_i140147547023440.inst","c140147471456208.out"],
          ["i140147472252176_i140147547023440.inst","c140147471458256.out"],
          ["i140147472297808_i140147547023440.inst","c140147471485712.out"],
          ["i140147472295696_i140147547023440.inst","c140147471486224.out"],
          ["i140147472296528_i140147547023440.inst","c140147471486288.out"],
          ["i140147472297360_i140147547023440.inst","c140147471524048.out"],
          ["i140147472297360_i140147547023440.clk_en","c140147471524688.out"],
          ["i140147472296528_i140147547023440.clk_en","c140147471524880.out"],
          ["i140147472295696_i140147547023440.clk_en","c140147471525072.out"],
          ["i140147472297808_i140147547023440.clk_en","c140147471525264.out"],
          ["i140147472295376_i140147547023440.clk_en","c140147471525456.out"],
          ["i140147472252176_i140147547023440.clk_en","c140147471525648.out"],
          ["i140147472251600_i140147547023440.clk_en","c140147471525840.out"],
          ["i140147472294864_i140147547023440.clk_en","c140147471526160.out"],
          ["i140147472295312_i140147547023440.clk_en","c140147471526352.out"],
          ["i140147472294864_i140147547023440.inputs0","i140147472251600_i140147547023440.O0"],
          ["i140147472252176_i140147547023440.O0","i140147472251600_i140147547023440.inputs0"],
          ["self.in1_lxy_stencil.1","i140147472251600_i140147547023440.inputs1"],
          ["i140147472295376_i140147547023440.O0","i140147472252176_i140147547023440.inputs0"],
          ["self.in1_lxy_stencil.2","i140147472252176_i140147547023440.inputs1"],
          ["i140147472295312_i140147547023440.inputs0","i140147472294864_i140147547023440.O0"],
          ["self.in0_lgxy_stencil.0","i140147472294864_i140147547023440.inputs1"],
          ["self.out_lgxy_stencil","i140147472295312_i140147547023440.O0"],
          ["self.in1_lxy_stencil.0","i140147472295312_i140147547023440.inputs1"],
          ["i140147472297808_i140147547023440.O0","i140147472295376_i140147547023440.inputs0"],
          ["self.in1_lxy_stencil.3","i140147472295376_i140147547023440.inputs1"],
          ["i140147472297808_i140147547023440.inputs0","i140147472295696_i140147547023440.O0"],
          ["i140147472296528_i140147547023440.O0","i140147472295696_i140147547023440.inputs0"],
          ["self.in1_lxy_stencil.5","i140147472295696_i140147547023440.inputs1"],
          ["i140147472297360_i140147547023440.O0","i140147472296528_i140147547023440.inputs0"],
          ["self.in1_lxy_stencil.6","i140147472296528_i140147547023440.inputs1"],
          ["self.in1_lxy_stencil.8","i140147472297360_i140147547023440.inputs0"],
          ["self.in1_lxy_stencil.7","i140147472297360_i140147547023440.inputs1"],
          ["self.in1_lxy_stencil.4","i140147472297808_i140147547023440.inputs1"]
        ]
      },
      "hcompute_lgxy_stencil":{
        "type":["Record",[
          ["out_lgxy_stencil",["Array",16,"Bit"]]
        ]],
        "instances":{
          "c140147472185232":{
            "genref":"coreir.const",
            "genargs":{"width":["Int",55]},
            "modargs":{"value":[["BitVector",55],"55'h0000200005294a"]}
          },
          "c140147472216208":{
            "modref":"corebit.const",
            "modargs":{"value":["Bool",true]}
          },
          "i140147519646352_i140147520043280":{
            "modref":"global.PE"
          }
        },
        "connections":[
          ["i140147519646352_i140147520043280.inst","c140147472185232.out"],
          ["i140147519646352_i140147520043280.clk_en","c140147472216208.out"],
          ["self.out_lgxy_stencil","i140147519646352_i140147520043280.O0"]
        ]
      },
      "hcompute_lgyy_stencil_1":{
        "type":["Record",[
          ["in0_lgyy_stencil",["Array",1,["Array",16,"BitIn"]]],
          ["in1_lyy_stencil",["Array",9,["Array",16,"BitIn"]]],
          ["out_lgyy_stencil",["Array",16,"Bit"]]
        ]],
        "instances":{
          "c140147469439568":{
            "genref":"coreir.const",
            "genargs":{"width":["Int",55]},
            "modargs":{"value":[["BitVector",55],"55'h00208ffff5294a"]}
          },
          "c140147469440016":{
            "genref":"coreir.const",
            "genargs":{"width":["Int",55]},
            "modargs":{"value":[["BitVector",55],"55'h00208ffff5294a"]}
          },
          "c140147469442448":{
            "genref":"coreir.const",
            "genargs":{"width":["Int",55]},
            "modargs":{"value":[["BitVector",55],"55'h00208ffff5294a"]}
          },
          "c140147469481680":{
            "genref":"coreir.const",
            "genargs":{"width":["Int",55]},
            "modargs":{"value":[["BitVector",55],"55'h00208ffff5294a"]}
          },
          "c140147469482320":{
            "genref":"coreir.const",
            "genargs":{"width":["Int",55]},
            "modargs":{"value":[["BitVector",55],"55'h00208ffff5294a"]}
          },
          "c140147469495888":{
            "genref":"coreir.const",
            "genargs":{"width":["Int",55]},
            "modargs":{"value":[["BitVector",55],"55'h00208ffff5294a"]}
          },
          "c140147469496080":{
            "genref":"coreir.const",
            "genargs":{"width":["Int",55]},
            "modargs":{"value":[["BitVector",55],"55'h00208ffff5294a"]}
          },
          "c140147469541648":{
            "genref":"coreir.const",
            "genargs":{"width":["Int",55]},
            "modargs":{"value":[["BitVector",55],"55'h00208ffff5294a"]}
          },
          "c140147469542096":{
            "genref":"coreir.const",
            "genargs":{"width":["Int",55]},
            "modargs":{"value":[["BitVector",55],"55'h00208ffff5294a"]}
          },
          "c140147469542736":{
            "modref":"corebit.const",
            "modargs":{"value":["Bool",true]}
          },
          "c140147469542928":{
            "modref":"corebit.const",
            "modargs":{"value":["Bool",true]}
          },
          "c140147469543120":{
            "modref":"corebit.const",
            "modargs":{"value":["Bool",true]}
          },
          "c140147469543312":{
            "modref":"corebit.const",
            "modargs":{"value":["Bool",true]}
          },
          "c140147469543504":{
            "modref":"corebit.const",
            "modargs":{"value":["Bool",true]}
          },
          "c140147469543696":{
            "modref":"corebit.const",
            "modargs":{"value":["Bool",true]}
          },
          "c140147469543888":{
            "modref":"corebit.const",
            "modargs":{"value":["Bool",true]}
          },
          "c140147469544208":{
            "modref":"corebit.const",
            "modargs":{"value":["Bool",true]}
          },
          "c140147469544400":{
            "modref":"corebit.const",
            "modargs":{"value":["Bool",true]}
          },
          "i140147470265552_i140147547023440":{
            "modref":"global.PE"
          },
          "i140147470307664_i140147547023440":{
            "modref":"global.PE"
          },
          "i140147470308816_i140147547023440":{
            "modref":"global.PE"
          },
          "i140147470309072_i140147547023440":{
            "modref":"global.PE"
          },
          "i140147470309328_i140147547023440":{
            "modref":"global.PE"
          },
          "i140147470309648_i140147547023440":{
            "modref":"global.PE"
          },
          "i140147470310160_i140147547023440":{
            "modref":"global.PE"
          },
          "i140147470310480_i140147547023440":{
            "modref":"global.PE"
          },
          "i140147470310928_i140147547023440":{
            "modref":"global.PE"
          }
        },
        "connections":[
          ["i140147470307664_i140147547023440.inst","c140147469439568.out"],
          ["i140147470265552_i140147547023440.inst","c140147469440016.out"],
          ["i140147470310928_i140147547023440.inst","c140147469442448.out"],
          ["i140147470309328_i140147547023440.inst","c140147469481680.out"],
          ["i140147470309072_i140147547023440.inst","c140147469482320.out"],
          ["i140147470308816_i140147547023440.inst","c140147469495888.out"],
          ["i140147470309648_i140147547023440.inst","c140147469496080.out"],
          ["i140147470310480_i140147547023440.inst","c140147469541648.out"],
          ["i140147470310160_i140147547023440.inst","c140147469542096.out"],
          ["i140147470310160_i140147547023440.clk_en","c140147469542736.out"],
          ["i140147470310480_i140147547023440.clk_en","c140147469542928.out"],
          ["i140147470309648_i140147547023440.clk_en","c140147469543120.out"],
          ["i140147470308816_i140147547023440.clk_en","c140147469543312.out"],
          ["i140147470309328_i140147547023440.clk_en","c140147469543504.out"],
          ["i140147470309072_i140147547023440.clk_en","c140147469543696.out"],
          ["i140147470265552_i140147547023440.clk_en","c140147469543888.out"],
          ["i140147470307664_i140147547023440.clk_en","c140147469544208.out"],
          ["i140147470310928_i140147547023440.clk_en","c140147469544400.out"],
          ["i140147470307664_i140147547023440.inputs0","i140147470265552_i140147547023440.O0"],
          ["i140147470309072_i140147547023440.O0","i140147470265552_i140147547023440.inputs0"],
          ["self.in1_lyy_stencil.1","i140147470265552_i140147547023440.inputs1"],
          ["i140147470310928_i140147547023440.inputs0","i140147470307664_i140147547023440.O0"],
          ["self.in0_lgyy_stencil.0","i140147470307664_i140147547023440.inputs1"],
          ["i140147470309328_i140147547023440.inputs0","i140147470308816_i140147547023440.O0"],
          ["i140147470309648_i140147547023440.O0","i140147470308816_i140147547023440.inputs0"],
          ["self.in1_lyy_stencil.4","i140147470308816_i140147547023440.inputs1"],
          ["i140147470309328_i140147547023440.O0","i140147470309072_i140147547023440.inputs0"],
          ["self.in1_lyy_stencil.2","i140147470309072_i140147547023440.inputs1"],
          ["self.in1_lyy_stencil.3","i140147470309328_i140147547023440.inputs1"],
          ["i140147470310480_i140147547023440.O0","i140147470309648_i140147547023440.inputs0"],
          ["self.in1_lyy_stencil.5","i140147470309648_i140147547023440.inputs1"],
          ["i140147470310480_i140147547023440.inputs0","i140147470310160_i140147547023440.O0"],
          ["self.in1_lyy_stencil.8","i140147470310160_i140147547023440.inputs0"],
          ["self.in1_lyy_stencil.7","i140147470310160_i140147547023440.inputs1"],
          ["self.in1_lyy_stencil.6","i140147470310480_i140147547023440.inputs1"],
          ["self.out_lgyy_stencil","i140147470310928_i140147547023440.O0"],
          ["self.in1_lyy_stencil.0","i140147470310928_i140147547023440.inputs1"]
        ]
      },
      "hcompute_lgyy_stencil":{
        "type":["Record",[
          ["out_lgyy_stencil",["Array",16,"Bit"]]
        ]],
        "instances":{
          "c140147470229968":{
            "modref":"corebit.const",
            "modargs":{"value":["Bool",true]}
          },
          "c140147470230736":{
            "genref":"coreir.const",
            "genargs":{"width":["Int",55]},
            "modargs":{"value":[["BitVector",55],"55'h0000200005294a"]}
          },
          "i140147471526608_i140147520043280":{
            "modref":"global.PE"
          }
        },
        "connections":[
          ["i140147471526608_i140147520043280.clk_en","c140147470229968.out"],
          ["i140147471526608_i140147520043280.inst","c140147470230736.out"],
          ["self.out_lgyy_stencil","i140147471526608_i140147520043280.O0"]
        ]
      },
      "hcompute_lxx_stencil":{
        "type":["Record",[
          ["in0_grad_x_unclamp_stencil",["Array",1,["Array",16,"BitIn"]]],
          ["out_lxx_stencil",["Array",16,"Bit"]]
        ]],
        "instances":{
          "c140147468838160":{
            "genref":"coreir.const",
            "genargs":{"width":["Int",55]},
            "modargs":{"value":[["BitVector",55],"55'h003040002518c5"]}
          },
          "c140147468838352":{
            "genref":"coreir.const",
            "genargs":{"width":["Int",55]},
            "modargs":{"value":[["BitVector",55],"55'h00002ff4c5294a"]}
          },
          "c140147468840016":{
            "genref":"coreir.const",
            "genargs":{"width":["Int",55]},
            "modargs":{"value":[["BitVector",55],"55'h00000000000000"]}
          },
          "c140147468840144":{
            "modref":"corebit.const",
            "modargs":{"value":["Bool",true]}
          },
          "c140147468867280":{
            "genref":"coreir.const",
            "genargs":{"width":["Int",55]},
            "modargs":{"value":[["BitVector",55],"55'h002060000518c5"]}
          },
          "c140147468868048":{
            "genref":"coreir.const",
            "genargs":{"width":["Int",55]},
            "modargs":{"value":[["BitVector",55],"55'h0000200065294a"]}
          },
          "c140147468868944":{
            "modref":"corebit.const",
            "modargs":{"value":["Bool",true]}
          },
          "c140147468887376":{
            "genref":"coreir.const",
            "genargs":{"width":["Int",55]},
            "modargs":{"value":[["BitVector",55],"55'h00087800044212"]}
          },
          "c140147468887568":{
            "genref":"coreir.const",
            "genargs":{"width":["Int",55]},
            "modargs":{"value":[["BitVector",55],"55'h0000200b45294a"]}
          },
          "c140147468888336":{
            "modref":"corebit.const",
            "modargs":{"value":["Bool",true]}
          },
          "c140147468888784":{
            "modref":"corebit.const",
            "modargs":{"value":["Bool",true]}
          },
          "c140147468888976":{
            "modref":"corebit.const",
            "modargs":{"value":["Bool",true]}
          },
          "c140147468889168":{
            "modref":"corebit.const",
            "modargs":{"value":["Bool",true]}
          },
          "c140147468889232":{
            "modref":"corebit.const",
            "modargs":{"value":["Bool",true]}
          },
          "i140147469684816_i140147536569552":{
            "modref":"global.PE"
          },
          "i140147469686544_i140147536252752":{
            "modref":"global.PE"
          },
          "i140147469686672_i140147549778000":{
            "modref":"global.PE"
          },
          "i140147469687312_i140147520043280":{
            "modref":"global.PE"
          },
          "i140147469688336_i140147520043280":{
            "modref":"global.PE"
          },
          "i140147469688784_i140147520043280":{
            "modref":"global.PE"
          },
          "i140147469690320_i140147545185680":{
            "modref":"global.PE"
          }
        },
        "connections":[
          ["i140147469686672_i140147549778000.inst","c140147468838160.out"],
          ["i140147469688784_i140147520043280.inst","c140147468838352.out"],
          ["i140147469684816_i140147536569552.inst","c140147468840016.out"],
          ["i140147469688784_i140147520043280.clk_en","c140147468840144.out"],
          ["i140147469690320_i140147545185680.inst","c140147468867280.out"],
          ["i140147469688336_i140147520043280.inst","c140147468868048.out"],
          ["i140147469688336_i140147520043280.clk_en","c140147468868944.out"],
          ["i140147469686544_i140147536252752.inst","c140147468887376.out"],
          ["i140147469687312_i140147520043280.inst","c140147468887568.out"],
          ["i140147469687312_i140147520043280.clk_en","c140147468888336.out"],
          ["i140147469686672_i140147549778000.clk_en","c140147468888784.out"],
          ["i140147469686544_i140147536252752.clk_en","c140147468888976.out"],
          ["i140147469684816_i140147536569552.clk_en","c140147468889168.out"],
          ["i140147469690320_i140147545185680.clk_en","c140147468889232.out"],
          ["i140147469690320_i140147545185680.inputs1","i140147469684816_i140147536569552.O0"],
          ["i140147469686672_i140147549778000.O0","i140147469684816_i140147536569552.inputs0"],
          ["i140147469686672_i140147549778000.O0","i140147469684816_i140147536569552.inputs1"],
          ["i140147469686672_i140147549778000.inputs1","i140147469686544_i140147536252752.O0"],
          ["i140147469687312_i140147520043280.O0","i140147469686544_i140147536252752.inputs0"],
          ["self.in0_grad_x_unclamp_stencil.0","i140147469686544_i140147536252752.inputs1"],
          ["i140147469688784_i140147520043280.O0","i140147469686672_i140147549778000.inputs0"],
          ["i140147469690320_i140147545185680.inputs0","i140147469688336_i140147520043280.O0"],
          ["self.out_lxx_stencil","i140147469690320_i140147545185680.O0"]
        ]
      },
      "hcompute_lxy_stencil":{
        "type":["Record",[
          ["in0_grad_x_unclamp_stencil",["Array",1,["Array",16,"BitIn"]]],
          ["in1_grad_y_unclamp_stencil",["Array",1,["Array",16,"BitIn"]]],
          ["out_lxy_stencil",["Array",16,"Bit"]]
        ]],
        "instances":{
          "c140147468284240":{
            "genref":"coreir.const",
            "genargs":{"width":["Int",55]},
            "modargs":{"value":[["BitVector",55],"55'h00002ff4c5294a"]}
          },
          "c140147468285008":{
            "modref":"corebit.const",
            "modargs":{"value":["Bool",true]}
          },
          "c140147468285328":{
            "genref":"coreir.const",
            "genargs":{"width":["Int",55]},
            "modargs":{"value":[["BitVector",55],"55'h0000200b45294a"]}
          },
          "c140147468286160":{
            "genref":"coreir.const",
            "genargs":{"width":["Int",55]},
            "modargs":{"value":[["BitVector",55],"55'h00087800044212"]}
          },
          "c140147468286352":{
            "modref":"corebit.const",
            "modargs":{"value":["Bool",true]}
          },
          "c140147468286800":{
            "modref":"corebit.const",
            "modargs":{"value":["Bool",true]}
          },
          "c140147468287184":{
            "modref":"corebit.const",
            "modargs":{"value":["Bool",true]}
          },
          "c140147468287248":{
            "modref":"corebit.const",
            "modargs":{"value":["Bool",true]}
          },
          "c140147468287568":{
            "modref":"corebit.const",
            "modargs":{"value":["Bool",true]}
          },
          "c140147468811920":{
            "genref":"coreir.const",
            "genargs":{"width":["Int",55]},
            "modargs":{"value":[["BitVector",55],"55'h002060000518c5"]}
          },
          "c140147521454992":{
            "modref":"corebit.const",
            "modargs":{"value":["Bool",true]}
          },
          "c140147521455376":{
            "genref":"coreir.const",
            "genargs":{"width":["Int",55]},
            "modargs":{"value":[["BitVector",55],"55'h0000200065294a"]}
          },
          "c140147521456656":{
            "genref":"coreir.const",
            "genargs":{"width":["Int",55]},
            "modargs":{"value":[["BitVector",55],"55'h00000000000000"]}
          },
          "c140147521463568":{
            "modref":"corebit.const",
            "modargs":{"value":["Bool",true]}
          },
          "c140147521463888":{
            "genref":"coreir.const",
            "genargs":{"width":["Int",55]},
            "modargs":{"value":[["BitVector",55],"55'h00087800044212"]}
          },
          "c140147521464720":{
            "genref":"coreir.const",
            "genargs":{"width":["Int",55]},
            "modargs":{"value":[["BitVector",55],"55'h003040002518c5"]}
          },
          "c140147521465168":{
            "genref":"coreir.const",
            "genargs":{"width":["Int",55]},
            "modargs":{"value":[["BitVector",55],"55'h0000200b45294a"]}
          },
          "c140147521465232":{
            "genref":"coreir.const",
            "genargs":{"width":["Int",55]},
            "modargs":{"value":[["BitVector",55],"55'h00002ff4c5294a"]}
          },
          "c140147532096528":{
            "modref":"corebit.const",
            "modargs":{"value":["Bool",true]}
          },
          "c140147532098640":{
            "modref":"corebit.const",
            "modargs":{"value":["Bool",true]}
          },
          "c140147532098832":{
            "modref":"corebit.const",
            "modargs":{"value":["Bool",true]}
          },
          "c140147532099088":{
            "genref":"coreir.const",
            "genargs":{"width":["Int",55]},
            "modargs":{"value":[["BitVector",55],"55'h003040002518c5"]}
          },
          "i140147468591184_i140147536569552":{
            "modref":"global.PE"
          },
          "i140147468591632_i140147549778000":{
            "modref":"global.PE"
          },
          "i140147468592016_i140147545185680":{
            "modref":"global.PE"
          },
          "i140147468592144_i140147520043280":{
            "modref":"global.PE"
          },
          "i140147468592208_i140147520043280":{
            "modref":"global.PE"
          },
          "i140147468592912_i140147520043280":{
            "modref":"global.PE"
          },
          "i140147468593168_i140147520043280":{
            "modref":"global.PE"
          },
          "i140147468593296_i140147520043280":{
            "modref":"global.PE"
          },
          "i140147468597200_i140147536252752":{
            "modref":"global.PE"
          },
          "i140147468597328_i140147549778000":{
            "modref":"global.PE"
          },
          "i140147468597584_i140147536252752":{
            "modref":"global.PE"
          }
        },
        "connections":[
          ["i140147468592144_i140147520043280.inst","c140147468284240.out"],
          ["i140147468597328_i140147549778000.clk_en","c140147468285008.out"],
          ["i140147468592208_i140147520043280.inst","c140147468285328.out"],
          ["i140147468597200_i140147536252752.inst","c140147468286160.out"],
          ["i140147468597200_i140147536252752.clk_en","c140147468286352.out"],
          ["i140147468592208_i140147520043280.clk_en","c140147468286800.out"],
          ["i140147468591184_i140147536569552.clk_en","c140147468287184.out"],
          ["i140147468592016_i140147545185680.clk_en","c140147468287248.out"],
          ["i140147468592144_i140147520043280.clk_en","c140147468287568.out"],
          ["i140147468592016_i140147545185680.inst","c140147468811920.out"],
          ["i140147468593168_i140147520043280.clk_en","c140147521454992.out"],
          ["i140147468593168_i140147520043280.inst","c140147521455376.out"],
          ["i140147468591184_i140147536569552.inst","c140147521456656.out"],
          ["i140147468593296_i140147520043280.clk_en","c140147521463568.out"],
          ["i140147468597584_i140147536252752.inst","c140147521463888.out"],
          ["i140147468591632_i140147549778000.inst","c140147521464720.out"],
          ["i140147468592912_i140147520043280.inst","c140147521465168.out"],
          ["i140147468593296_i140147520043280.inst","c140147521465232.out"],
          ["i140147468591632_i140147549778000.clk_en","c140147532096528.out"],
          ["i140147468597584_i140147536252752.clk_en","c140147532098640.out"],
          ["i140147468592912_i140147520043280.clk_en","c140147532098832.out"],
          ["i140147468597328_i140147549778000.inst","c140147532099088.out"],
          ["i140147468592016_i140147545185680.inputs1","i140147468591184_i140147536569552.O0"],
          ["i140147468591632_i140147549778000.O0","i140147468591184_i140147536569552.inputs0"],
          ["i140147468597328_i140147549778000.O0","i140147468591184_i140147536569552.inputs1"],
          ["i140147468593296_i140147520043280.O0","i140147468591632_i140147549778000.inputs0"],
          ["i140147468597584_i140147536252752.O0","i140147468591632_i140147549778000.inputs1"],
          ["self.out_lxy_stencil","i140147468592016_i140147545185680.O0"],
          ["i140147468593168_i140147520043280.O0","i140147468592016_i140147545185680.inputs0"],
          ["i140147468597328_i140147549778000.inputs0","i140147468592144_i140147520043280.O0"],
          ["i140147468597200_i140147536252752.inputs0","i140147468592208_i140147520043280.O0"],
          ["i140147468597584_i140147536252752.inputs0","i140147468592912_i140147520043280.O0"],
          ["i140147468597328_i140147549778000.inputs1","i140147468597200_i140147536252752.O0"],
          ["self.in0_grad_x_unclamp_stencil.0","i140147468597200_i140147536252752.inputs1"],
          ["self.in1_grad_y_unclamp_stencil.0","i140147468597584_i140147536252752.inputs1"]
        ]
      },
      "hcompute_lyy_stencil":{
        "type":["Record",[
          ["in0_grad_y_unclamp_stencil",["Array",1,["Array",16,"BitIn"]]],
          ["out_lyy_stencil",["Array",16,"Bit"]]
        ]],
        "instances":{
          "c140147467560464":{
            "modref":"corebit.const",
            "modargs":{"value":["Bool",true]}
          },
          "c140147467560848":{
            "genref":"coreir.const",
            "genargs":{"width":["Int",55]},
            "modargs":{"value":[["BitVector",55],"55'h0000200065294a"]}
          },
          "c140147467562000":{
            "genref":"coreir.const",
            "genargs":{"width":["Int",55]},
            "modargs":{"value":[["BitVector",55],"55'h002060000518c5"]}
          },
          "c140147467581200":{
            "genref":"coreir.const",
            "genargs":{"width":["Int",55]},
            "modargs":{"value":[["BitVector",55],"55'h003040002518c5"]}
          },
          "c140147467581392":{
            "genref":"coreir.const",
            "genargs":{"width":["Int",55]},
            "modargs":{"value":[["BitVector",55],"55'h00000000000000"]}
          },
          "c140147467582736":{
            "modref":"corebit.const",
            "modargs":{"value":["Bool",true]}
          },
          "c140147467582928":{
            "genref":"coreir.const",
            "genargs":{"width":["Int",55]},
            "modargs":{"value":[["BitVector",55],"55'h00002ff4c5294a"]}
          },
          "c140147467595984":{
            "modref":"corebit.const",
            "modargs":{"value":["Bool",true]}
          },
          "c140147467596304":{
            "genref":"coreir.const",
            "genargs":{"width":["Int",55]},
            "modargs":{"value":[["BitVector",55],"55'h00087800044212"]}
          },
          "c140147467596560":{
            "genref":"coreir.const",
            "genargs":{"width":["Int",55]},
            "modargs":{"value":[["BitVector",55],"55'h0000200b45294a"]}
          },
          "c140147467598480":{
            "modref":"corebit.const",
            "modargs":{"value":["Bool",true]}
          },
          "c140147467598672":{
            "modref":"corebit.const",
            "modargs":{"value":["Bool",true]}
          },
          "c140147467599248":{
            "modref":"corebit.const",
            "modargs":{"value":["Bool",true]}
          },
          "c140147467599504":{
            "modref":"corebit.const",
            "modargs":{"value":["Bool",true]}
          },
          "i140147467924688_i140147545185680":{
            "modref":"global.PE"
          },
          "i140147467926096_i140147536569552":{
            "modref":"global.PE"
          },
          "i140147467926736_i140147549778000":{
            "modref":"global.PE"
          },
          "i140147467933392_i140147536252752":{
            "modref":"global.PE"
          },
          "i140147467933584_i140147520043280":{
            "modref":"global.PE"
          },
          "i140147467933904_i140147520043280":{
            "modref":"global.PE"
          },
          "i140147467933968_i140147520043280":{
            "modref":"global.PE"
          }
        },
        "connections":[
          ["i140147467933904_i140147520043280.clk_en","c140147467560464.out"],
          ["i140147467933904_i140147520043280.inst","c140147467560848.out"],
          ["i140147467924688_i140147545185680.inst","c140147467562000.out"],
          ["i140147467926736_i140147549778000.inst","c140147467581200.out"],
          ["i140147467926096_i140147536569552.inst","c140147467581392.out"],
          ["i140147467933968_i140147520043280.clk_en","c140147467582736.out"],
          ["i140147467933968_i140147520043280.inst","c140147467582928.out"],
          ["i140147467924688_i140147545185680.clk_en","c140147467595984.out"],
          ["i140147467933392_i140147536252752.inst","c140147467596304.out"],
          ["i140147467933584_i140147520043280.inst","c140147467596560.out"],
          ["i140147467933584_i140147520043280.clk_en","c140147467598480.out"],
          ["i140147467926096_i140147536569552.clk_en","c140147467598672.out"],
          ["i140147467933392_i140147536252752.clk_en","c140147467599248.out"],
          ["i140147467926736_i140147549778000.clk_en","c140147467599504.out"],
          ["self.out_lyy_stencil","i140147467924688_i140147545185680.O0"],
          ["i140147467933904_i140147520043280.O0","i140147467924688_i140147545185680.inputs0"],
          ["i140147467926096_i140147536569552.O0","i140147467924688_i140147545185680.inputs1"],
          ["i140147467926736_i140147549778000.O0","i140147467926096_i140147536569552.inputs0"],
          ["i140147467926736_i140147549778000.O0","i140147467926096_i140147536569552.inputs1"],
          ["i140147467933968_i140147520043280.O0","i140147467926736_i140147549778000.inputs0"],
          ["i140147467933392_i140147536252752.O0","i140147467926736_i140147549778000.inputs1"],
          ["i140147467933584_i140147520043280.O0","i140147467933392_i140147536252752.inputs0"],
          ["self.in0_grad_y_unclamp_stencil.0","i140147467933392_i140147536252752.inputs1"]
        ]
      },
      "hcompute_padded16_global_wrapper_stencil":{
        "type":["Record",[
          ["in0_padded16_stencil",["Array",1,["Array",16,"BitIn"]]],
          ["out_padded16_global_wrapper_stencil",["Array",16,"Bit"]]
        ]],
        "connections":[
          ["self.out_padded16_global_wrapper_stencil","self.in0_padded16_stencil.0"]
        ]
      }
    }
  }
}
}
